pythonProject1/__init__.py
pythonProject1-0.0.1.dist-info/METADATA
pythonProject1-0.0.1.dist-info/WHEEL
pythonProject1-0.0.1.dist-info/top_level.txt
pythonProject1-0.0.1.dist-info/RECORD
